ubscrape/__init__.py
ubscrape/__main__.py
ubscrape/command_line.py
ubscrape/constants.py
ubscrape/db.py
ubscrape/definitions.py
ubscrape/jsonwriter.py
ubscrape/setup.py
ubscrape/words.py
ubscrape-0.1.4.dist-info/LICENSE.txt
ubscrape-0.1.4.dist-info/METADATA
ubscrape-0.1.4.dist-info/WHEEL
ubscrape-0.1.4.dist-info/entry_points.txt
ubscrape-0.1.4.dist-info/top_level.txt
ubscrape-0.1.4.dist-info/RECORD
