Metadata-Version: 2.1
Name: ubscrape
Version: 0.1.4
Summary: Scrapes Urban Dictionary and stores it locally.
Home-page: http://github.com/samuelstevens/ubscrape
Author: Samuel Stevens
Author-email: samuel.robert.stevens@gmail.com
License: MIT
Platform: UNKNOWN
Requires-Dist: bs4
Requires-Dist: requests
